<annotation>
	<folder></folder>
	<filename>00ff10580fd2c0a3_jpg.rf.2d2aa780fca1a22b7bd9b1bb739d0eac.jpg</filename>
	<path>00ff10580fd2c0a3_jpg.rf.2d2aa780fca1a22b7bd9b1bb739d0eac.jpg</path>
	<source>
		<database>roboflow.ai</database>
	</source>
	<size>
		<width>1024</width>
		<height>685</height>
		<depth>3</depth>
	</size>
	<segmented>0</segmented>
	<object>
		<name>License_Plate</name>
		<pose>Unspecified</pose>
		<truncated>0</truncated>
		<difficult>0</difficult>
		<occluded>0</occluded>
		<bndbox>
			<xmin>491</xmin>
			<xmax>634</xmax>
			<ymin>453</ymin>
			<ymax>520</ymax>
		</bndbox>
	</object>
</annotation>
