<annotation>
	<folder></folder>
	<filename>CarLongPlate899_jpg.rf.140d35f8501393a205236ac955e0c9e7.jpg</filename>
	<path>CarLongPlate899_jpg.rf.140d35f8501393a205236ac955e0c9e7.jpg</path>
	<source>
		<database>roboflow.ai</database>
	</source>
	<size>
		<width>472</width>
		<height>303</height>
		<depth>3</depth>
	</size>
	<segmented>0</segmented>
	<object>
		<name>License_Plate</name>
		<pose>Unspecified</pose>
		<truncated>0</truncated>
		<difficult>0</difficult>
		<occluded>0</occluded>
		<bndbox>
			<xmin>186</xmin>
			<xmax>298</xmax>
			<ymin>57</ymin>
			<ymax>88</ymax>
		</bndbox>
	</object>
</annotation>
