<annotation>
	<folder></folder>
	<filename>CarLongPlate918_jpg.rf.62ae8b050c64d4590878387f1c5e3915.jpg</filename>
	<path>CarLongPlate918_jpg.rf.62ae8b050c64d4590878387f1c5e3915.jpg</path>
	<source>
		<database>roboflow.ai</database>
	</source>
	<size>
		<width>472</width>
		<height>303</height>
		<depth>3</depth>
	</size>
	<segmented>0</segmented>
	<object>
		<name>License_Plate</name>
		<pose>Unspecified</pose>
		<truncated>0</truncated>
		<difficult>0</difficult>
		<occluded>0</occluded>
		<bndbox>
			<xmin>244</xmin>
			<xmax>335</xmax>
			<ymin>169</ymin>
			<ymax>202</ymax>
		</bndbox>
	</object>
</annotation>
